{
  "date": "2013-11-12",
  "positions": [
    {
      "name": "ALTERA CORP",
      "cusip": "021441100",
      "shares": 2231150,
      "value": 82910000
    },
    {
      "name": "ALTERA CORP",
      "cusip": "021441100",
      "shares": 3420745,
      "value": 127115000
    },
    {
      "name": "ANALOG DEVICES INC",
      "cusip": "032654105",
      "shares": 4025930,
      "value": 189420000
    },
    {
      "name": "ANALOG DEVICES INC",
      "cusip": "032654105",
      "shares": 2617239,
      "value": 123141000
    },
    {
      "name": "BAIDU INC",
      "cusip": "056752108",
      "shares": 1411900,
      "value": 219099000
    },
    {
      "name": "BAIDU INC",
      "cusip": "056752108",
      "shares": 925252,
      "value": 143581000
    },
    {
      "name": "BANCO BRADESCO S A",
      "cusip": "059460303",
      "shares": 1979518,
      "value": 27476000
    },
    {
      "name": "BANCO BRADESCO S A",
      "cusip": "059460303",
      "shares": 3006245,
      "value": 41727000
    },
    {
      "name": "BRINKS CO",
      "cusip": "109696104",
      "shares": 1236567,
      "value": 34995000
    },
    {
      "name": "BRINKS CO",
      "cusip": "109696104",
      "shares": 1898984,
      "value": 53741000
    },
    {
      "name": "COCA COLA CO",
      "cusip": "191216100",
      "shares": 2824152,
      "value": 106979000
    },
    {
      "name": "COCA COLA CO",
      "cusip": "191216100",
      "shares": 4329500,
      "value": 164001000
    },
    {
      "name": "COLGATE PALMOLIVE CO",
      "cusip": "194162103",
      "shares": 717280,
      "value": 42535000
    },
    {
      "name": "COLGATE PALMOLIVE CO",
      "cusip": "194162103",
      "shares": 1096572,
      "value": 65027000
    },
    {
      "name": "COMPANHIA DE BEBIDAS DAS AME",
      "cusip": "20441W203",
      "shares": 2682150,
      "value": 102860000
    },
    {
      "name": "COMPANHIA DE BEBIDAS DAS AME",
      "cusip": "20441W203",
      "shares": 1765510,
      "value": 67707000
    },
    {
      "name": "CREDIT ACCEP CORP MICH",
      "cusip": "225310101",
      "shares": 182096,
      "value": 20178000
    },
    {
      "name": "CREDIT ACCEP CORP MICH",
      "cusip": "225310101",
      "shares": 279597,
      "value": 30982000
    },
    {
      "name": "ECOLAB INC",
      "cusip": "278865100",
      "shares": 1547971,
      "value": 152878000
    },
    {
      "name": "ECOLAB INC",
      "cusip": "278865100",
      "shares": 1010320,
      "value": 99779000
    },
    {
      "name": "FIDELITY NATL INFORMATION SV",
      "cusip": "31620M106",
      "shares": 3254651,
      "value": 151146000
    },
    {
      "name": "FIDELITY NATL INFORMATION SV",
      "cusip": "31620M106",
      "shares": 2118040,
      "value": 98362000
    },
    {
      "name": "GOOGLE INC",
      "cusip": "38259P508",
      "shares": 161100,
      "value": 141109000
    },
    {
      "name": "GOOGLE INC",
      "cusip": "38259P508",
      "shares": 247359,
      "value": 216664000
    },
    {
      "name": "GRAINGER W W INC",
      "cusip": "384802104",
      "shares": 134694,
      "value": 35251000
    },
    {
      "name": "GRAINGER W W INC",
      "cusip": "384802104",
      "shares": 209628,
      "value": 54862000
    },
    {
      "name": "HARLEY DAVIDSON INC",
      "cusip": "412822108",
      "shares": 2171559,
      "value": 139501000
    },
    {
      "name": "HARLEY DAVIDSON INC",
      "cusip": "412822108",
      "shares": 3333270,
      "value": 214129000
    },
    {
      "name": "LKQ CORP",
      "cusip": "501889208",
      "shares": 2185426,
      "value": 69628000
    },
    {
      "name": "LKQ CORP",
      "cusip": "501889208",
      "shares": 3350122,
      "value": 106735000
    },
    {
      "name": "OPENTABLE INC",
      "cusip": "68372A104",
      "shares": 3059,
      "value": 214000
    },
    {
      "name": "OPENTABLE INC",
      "cusip": "68372A104",
      "shares": 4741,
      "value": 332000
    },
    {
      "name": "PHILIP MORRIS INTL INC",
      "cusip": "718172109",
      "shares": 704229,
      "value": 60979000
    },
    {
      "name": "PHILIP MORRIS INTL INC",
      "cusip": "718172109",
      "shares": 457872,
      "value": 39647000
    },
    {
      "name": "PRICELINE COM INC",
      "cusip": "741503403",
      "shares": 119361,
      "value": 120668000
    },
    {
      "name": "PRICELINE COM INC",
      "cusip": "741503403",
      "shares": 183266,
      "value": 185273000
    },
    {
      "name": "SOLERA HOLDINGS INC",
      "cusip": "83421A104",
      "shares": 683242,
      "value": 36123000
    },
    {
      "name": "SOLERA HOLDINGS INC",
      "cusip": "83421A104",
      "shares": 1043864,
      "value": 55189000
    },
    {
      "name": "WATERS CORP",
      "cusip": "941848103",
      "shares": 419930,
      "value": 44601000
    },
    {
      "name": "WATERS CORP",
      "cusip": "941848103",
      "shares": 644985,
      "value": 68504000
    },
    {
      "name": "WILLIS GROUP HOLDINGS PUBLIC",
      "cusip": "G96666105",
      "shares": 1284382,
      "value": 55652000
    },
    {
      "name": "WILLIS GROUP HOLDINGS PUBLIC",
      "cusip": "G96666105",
      "shares": 841488,
      "value": 36462000
    }
  ]
}