{
  "form": "13F-HR",
  "date": "2026-05-14",
  "period": "2026-05-14",
  "accession": "0001172661-26-001911",
  "quarterKey": "2026-Q2",
  "positions": [
    {
      "name": "MICROSOFT CORP",
      "cusip": "594918104",
      "shares": 2845888,
      "value": 1053462402,
      "optionType": "STOCK",
      "typeInfo": {
        "label": "Stock",
        "badge": "bg-blue-100 text-blue-800 border-blue-200",
        "strategy": "equity"
      },
      "titleOfClass": "COM",
      "putCall": null
    },
    {
      "name": "ALPHABET INC",
      "cusip": "02079K107",
      "shares": 2946637,
      "value": 845272352,
      "optionType": "STOCK",
      "typeInfo": {
        "label": "Stock",
        "badge": "bg-blue-100 text-blue-800 border-blue-200",
        "strategy": "equity"
      },
      "titleOfClass": "CAP STK CL C",
      "putCall": null
    },
    {
      "name": "ELI LILLY & CO",
      "cusip": "532457108",
      "shares": 914557,
      "value": 841181778,
      "optionType": "STOCK",
      "typeInfo": {
        "label": "Stock",
        "badge": "bg-blue-100 text-blue-800 border-blue-200",
        "strategy": "equity"
      },
      "titleOfClass": "COM",
      "putCall": null
    },
    {
      "name": "BROADCOM INC",
      "cusip": "11135F101",
      "shares": 2697567,
      "value": 834924015,
      "optionType": "STOCK",
      "typeInfo": {
        "label": "Stock",
        "badge": "bg-blue-100 text-blue-800 border-blue-200",
        "strategy": "equity"
      },
      "titleOfClass": "COM",
      "putCall": null
    },
    {
      "name": "AMAZON COM INC",
      "cusip": "023135106",
      "shares": 3896739,
      "value": 811573863,
      "optionType": "STOCK",
      "typeInfo": {
        "label": "Stock",
        "badge": "bg-blue-100 text-blue-800 border-blue-200",
        "strategy": "equity"
      },
      "titleOfClass": "COM",
      "putCall": null
    },
    {
      "name": "MASTERCARD INCORPORATED",
      "cusip": "57636Q104",
      "shares": 1541388,
      "value": 770169816,
      "optionType": "STOCK",
      "typeInfo": {
        "label": "Stock",
        "badge": "bg-blue-100 text-blue-800 border-blue-200",
        "strategy": "equity"
      },
      "titleOfClass": "CL A",
      "putCall": null
    },
    {
      "name": "SERVICENOW INC",
      "cusip": "81762P102",
      "shares": 7269453,
      "value": 760021232,
      "optionType": "STOCK",
      "typeInfo": {
        "label": "Stock",
        "badge": "bg-blue-100 text-blue-800 border-blue-200",
        "strategy": "equity"
      },
      "titleOfClass": "COM",
      "putCall": null
    },
    {
      "name": "SHOPIFY INC",
      "cusip": "82509L107",
      "shares": 6306740,
      "value": 748105429,
      "optionType": "STOCK",
      "typeInfo": {
        "label": "Stock",
        "badge": "bg-blue-100 text-blue-800 border-blue-200",
        "strategy": "equity"
      },
      "titleOfClass": "CL A SUB VTG SHS",
      "putCall": null
    },
    {
      "name": "VISA INC",
      "cusip": "92826C839",
      "shares": 2445760,
      "value": 739206345,
      "optionType": "STOCK",
      "typeInfo": {
        "label": "Stock",
        "badge": "bg-blue-100 text-blue-800 border-blue-200",
        "strategy": "equity"
      },
      "titleOfClass": "COM CL A",
      "putCall": null
    },
    {
      "name": "ORACLE CORP",
      "cusip": "68389X105",
      "shares": 5024257,
      "value": 739118451,
      "optionType": "STOCK",
      "typeInfo": {
        "label": "Stock",
        "badge": "bg-blue-100 text-blue-800 border-blue-200",
        "strategy": "equity"
      },
      "titleOfClass": "COM",
      "putCall": null
    },
    {
      "name": "NVIDIA CORPORATION",
      "cusip": "67066G104",
      "shares": 4104247,
      "value": 715780775,
      "optionType": "STOCK",
      "typeInfo": {
        "label": "Stock",
        "badge": "bg-blue-100 text-blue-800 border-blue-200",
        "strategy": "equity"
      },
      "titleOfClass": "COM",
      "putCall": null
    },
    {
      "name": "COSTAR GROUP INC",
      "cusip": "22160N109",
      "shares": 12570368,
      "value": 507088654,
      "optionType": "STOCK",
      "typeInfo": {
        "label": "Stock",
        "badge": "bg-blue-100 text-blue-800 border-blue-200",
        "strategy": "equity"
      },
      "titleOfClass": "COM",
      "putCall": null
    },
    {
      "name": "MSCI INC",
      "cusip": "55354G100",
      "shares": 929509,
      "value": 501014820,
      "optionType": "STOCK",
      "typeInfo": {
        "label": "Stock",
        "badge": "bg-blue-100 text-blue-800 border-blue-200",
        "strategy": "equity"
      },
      "titleOfClass": "COM",
      "putCall": null
    },
    {
      "name": "ZOETIS INC",
      "cusip": "98978V103",
      "shares": 4223076,
      "value": 499209768,
      "optionType": "STOCK",
      "typeInfo": {
        "label": "Stock",
        "badge": "bg-blue-100 text-blue-800 border-blue-200",
        "strategy": "equity"
      },
      "titleOfClass": "CL A",
      "putCall": null
    },
    {
      "name": "STARBUCKS CORP",
      "cusip": "855244109",
      "shares": 5055488,
      "value": 452921141,
      "optionType": "STOCK",
      "typeInfo": {
        "label": "Stock",
        "badge": "bg-blue-100 text-blue-800 border-blue-200",
        "strategy": "equity"
      },
      "titleOfClass": "COM",
      "putCall": null
    },
    {
      "name": "AON PLC",
      "cusip": "G0403H108",
      "shares": 1354053,
      "value": 437061344,
      "optionType": "STOCK",
      "typeInfo": {
        "label": "Stock",
        "badge": "bg-blue-100 text-blue-800 border-blue-200",
        "strategy": "equity"
      },
      "titleOfClass": "SHS CL A",
      "putCall": null
    },
    {
      "name": "IDEXX LABS INC",
      "cusip": "45168D104",
      "shares": 695811,
      "value": 390969243,
      "optionType": "STOCK",
      "typeInfo": {
        "label": "Stock",
        "badge": "bg-blue-100 text-blue-800 border-blue-200",
        "strategy": "equity"
      },
      "titleOfClass": "COM",
      "putCall": null
    },
    {
      "name": "AIRBNB INC",
      "cusip": "009066101",
      "shares": 2273747,
      "value": 287128813,
      "optionType": "STOCK",
      "typeInfo": {
        "label": "Stock",
        "badge": "bg-blue-100 text-blue-800 border-blue-200",
        "strategy": "equity"
      },
      "titleOfClass": "COM CL A",
      "putCall": null
    },
    {
      "name": "INTUITIVE SURGICAL INC",
      "cusip": "46120E602",
      "shares": 606826,
      "value": 279740605,
      "optionType": "STOCK",
      "typeInfo": {
        "label": "Stock",
        "badge": "bg-blue-100 text-blue-800 border-blue-200",
        "strategy": "equity"
      },
      "titleOfClass": "COM NEW",
      "putCall": null
    },
    {
      "name": "META PLATFORMS INC",
      "cusip": "30303M102",
      "shares": 476663,
      "value": 272713407,
      "optionType": "STOCK",
      "typeInfo": {
        "label": "Stock",
        "badge": "bg-blue-100 text-blue-800 border-blue-200",
        "strategy": "equity"
      },
      "titleOfClass": "CL A",
      "putCall": null
    },
    {
      "name": "ACCENTURE PLC IRELAND",
      "cusip": "G1151C101",
      "shares": 1354748,
      "value": 268632941,
      "optionType": "STOCK",
      "typeInfo": {
        "label": "Stock",
        "badge": "bg-blue-100 text-blue-800 border-blue-200",
        "strategy": "equity"
      },
      "titleOfClass": "SHS CLASS A",
      "putCall": null
    },
    {
      "name": "SYNOPSYS INC",
      "cusip": "871607107",
      "shares": 671233,
      "value": 266130284,
      "optionType": "STOCK",
      "typeInfo": {
        "label": "Stock",
        "badge": "bg-blue-100 text-blue-800 border-blue-200",
        "strategy": "equity"
      },
      "titleOfClass": "COM",
      "putCall": null
    },
    {
      "name": "LAM RESEARCH CORP",
      "cusip": "512807306",
      "shares": 1054495,
      "value": 225303412,
      "optionType": "STOCK",
      "typeInfo": {
        "label": "Stock",
        "badge": "bg-blue-100 text-blue-800 border-blue-200",
        "strategy": "equity"
      },
      "titleOfClass": "COM NEW",
      "putCall": null
    },
    {
      "name": "UBER TECHNOLOGIES INC",
      "cusip": "90353T100",
      "shares": 2917928,
      "value": 209886531,
      "optionType": "STOCK",
      "typeInfo": {
        "label": "Stock",
        "badge": "bg-blue-100 text-blue-800 border-blue-200",
        "strategy": "equity"
      },
      "titleOfClass": "COM",
      "putCall": null
    },
    {
      "name": "ISHARES TR",
      "cusip": "464287614",
      "shares": 406863,
      "value": 173486508,
      "optionType": "STOCK",
      "typeInfo": {
        "label": "Stock",
        "badge": "bg-blue-100 text-blue-800 border-blue-200",
        "strategy": "equity"
      },
      "titleOfClass": "RUS 1000 GRW ETF",
      "putCall": null
    },
    {
      "name": "ROLLINS INC",
      "cusip": "775711104",
      "shares": 2177678,
      "value": 116309779,
      "optionType": "STOCK",
      "typeInfo": {
        "label": "Stock",
        "badge": "bg-blue-100 text-blue-800 border-blue-200",
        "strategy": "equity"
      },
      "titleOfClass": "COM",
      "putCall": null
    },
    {
      "name": "MERCADOLIBRE INC",
      "cusip": "58733R102",
      "shares": 34452,
      "value": 59567722,
      "optionType": "STOCK",
      "typeInfo": {
        "label": "Stock",
        "badge": "bg-blue-100 text-blue-800 border-blue-200",
        "strategy": "equity"
      },
      "titleOfClass": "COM",
      "putCall": null
    },
    {
      "name": "TAIWAN SEMICONDUCTOR MANUFAC",
      "cusip": "874039100",
      "shares": 174686,
      "value": 59035081,
      "optionType": "STOCK",
      "typeInfo": {
        "label": "Stock",
        "badge": "bg-blue-100 text-blue-800 border-blue-200",
        "strategy": "equity"
      },
      "titleOfClass": "SPONSORED ADS",
      "putCall": null
    },
    {
      "name": "SPOTIFY TECHNOLOGY S A",
      "cusip": "L8681T102",
      "shares": 107429,
      "value": 52093417,
      "optionType": "STOCK",
      "typeInfo": {
        "label": "Stock",
        "badge": "bg-blue-100 text-blue-800 border-blue-200",
        "strategy": "equity"
      },
      "titleOfClass": "SHS",
      "putCall": null
    },
    {
      "name": "ISHARES TR",
      "cusip": "464288257",
      "shares": 306415,
      "value": 42398594,
      "optionType": "STOCK",
      "typeInfo": {
        "label": "Stock",
        "badge": "bg-blue-100 text-blue-800 border-blue-200",
        "strategy": "equity"
      },
      "titleOfClass": "MSCI ACWI ETF",
      "putCall": null
    },
    {
      "name": "BOSTON SCIENTIFIC CORP",
      "cusip": "101137107",
      "shares": 579739,
      "value": 36378606,
      "optionType": "STOCK",
      "typeInfo": {
        "label": "Stock",
        "badge": "bg-blue-100 text-blue-800 border-blue-200",
        "strategy": "equity"
      },
      "titleOfClass": "COM",
      "putCall": null
    },
    {
      "name": "ASML HLDG NV",
      "cusip": "N07059210",
      "shares": 16072,
      "value": 21228760,
      "optionType": "STOCK",
      "typeInfo": {
        "label": "Stock",
        "badge": "bg-blue-100 text-blue-800 border-blue-200",
        "strategy": "equity"
      },
      "titleOfClass": "N Y REGISTRY SHS",
      "putCall": null
    },
    {
      "name": "NU HLDGS LTD",
      "cusip": "G6683N103",
      "shares": 1217238,
      "value": 17491709,
      "optionType": "STOCK",
      "typeInfo": {
        "label": "Stock",
        "badge": "bg-blue-100 text-blue-800 border-blue-200",
        "strategy": "equity"
      },
      "titleOfClass": "ORD SHS CL A",
      "putCall": null
    },
    {
      "name": "SAP SE",
      "cusip": "803054204",
      "shares": 66674,
      "value": 11415227,
      "optionType": "STOCK",
      "typeInfo": {
        "label": "Stock",
        "badge": "bg-blue-100 text-blue-800 border-blue-200",
        "strategy": "equity"
      },
      "titleOfClass": "SPON ADR",
      "putCall": null
    },
    {
      "name": "ARGAN INC",
      "cusip": "04010E109",
      "shares": 17981,
      "value": 9793352,
      "optionType": "STOCK",
      "typeInfo": {
        "label": "Stock",
        "badge": "bg-blue-100 text-blue-800 border-blue-200",
        "strategy": "equity"
      },
      "titleOfClass": "COM",
      "putCall": null
    },
    {
      "name": "POWELL INDS INC",
      "cusip": "739128106",
      "shares": 17485,
      "value": 9460784,
      "optionType": "STOCK",
      "typeInfo": {
        "label": "Stock",
        "badge": "bg-blue-100 text-blue-800 border-blue-200",
        "strategy": "equity"
      },
      "titleOfClass": "COM",
      "putCall": null
    },
    {
      "name": "BLOOM ENERGY CORP",
      "cusip": "093712107",
      "shares": 67231,
      "value": 9109128,
      "optionType": "STOCK",
      "typeInfo": {
        "label": "Stock",
        "badge": "bg-blue-100 text-blue-800 border-blue-200",
        "strategy": "equity"
      },
      "titleOfClass": "COM CL A",
      "putCall": null
    },
    {
      "name": "INTUIT",
      "cusip": "461202103",
      "shares": 19853,
      "value": 8583861,
      "optionType": "STOCK",
      "typeInfo": {
        "label": "Stock",
        "badge": "bg-blue-100 text-blue-800 border-blue-200",
        "strategy": "equity"
      },
      "titleOfClass": "COM",
      "putCall": null
    },
    {
      "name": "BEL FUSE INC",
      "cusip": "077347300",
      "shares": 43339,
      "value": 8580255,
      "optionType": "STOCK",
      "typeInfo": {
        "label": "Stock",
        "badge": "bg-blue-100 text-blue-800 border-blue-200",
        "strategy": "equity"
      },
      "titleOfClass": "CL B",
      "putCall": null
    },
    {
      "name": "CECO ENVIRONMENTAL CORP",
      "cusip": "125141101",
      "shares": 143231,
      "value": 8533703,
      "optionType": "STOCK",
      "typeInfo": {
        "label": "Stock",
        "badge": "bg-blue-100 text-blue-800 border-blue-200",
        "strategy": "equity"
      },
      "titleOfClass": "COM",
      "putCall": null
    },
    {
      "name": "DIGITALOCEAN HLDGS INC",
      "cusip": "25402D102",
      "shares": 96206,
      "value": 8252551,
      "optionType": "STOCK",
      "typeInfo": {
        "label": "Stock",
        "badge": "bg-blue-100 text-blue-800 border-blue-200",
        "strategy": "equity"
      },
      "titleOfClass": "COM",
      "putCall": null
    },
    {
      "name": "ALPHABET INC",
      "cusip": "02079K305",
      "shares": 28195,
      "value": 8107744,
      "optionType": "STOCK",
      "typeInfo": {
        "label": "Stock",
        "badge": "bg-blue-100 text-blue-800 border-blue-200",
        "strategy": "equity"
      },
      "titleOfClass": "CAP STK CL A",
      "putCall": null
    },
    {
      "name": "NETFLIX INC",
      "cusip": "64110L106",
      "shares": 83285,
      "value": 8007890,
      "optionType": "STOCK",
      "typeInfo": {
        "label": "Stock",
        "badge": "bg-blue-100 text-blue-800 border-blue-200",
        "strategy": "equity"
      },
      "titleOfClass": "COM",
      "putCall": null
    },
    {
      "name": "BWX TECHNOLOGIES INC",
      "cusip": "05605H100",
      "shares": 38123,
      "value": 7795772,
      "optionType": "STOCK",
      "typeInfo": {
        "label": "Stock",
        "badge": "bg-blue-100 text-blue-800 border-blue-200",
        "strategy": "equity"
      },
      "titleOfClass": "COM",
      "putCall": null
    },
    {
      "name": "VSE CORP",
      "cusip": "918284100",
      "shares": 42040,
      "value": 7752176,
      "optionType": "STOCK",
      "typeInfo": {
        "label": "Stock",
        "badge": "bg-blue-100 text-blue-800 border-blue-200",
        "strategy": "equity"
      },
      "titleOfClass": "COM",
      "putCall": null
    },
    {
      "name": "AMPRIUS TECHNOLOGIES INC",
      "cusip": "03214Q108",
      "shares": 422145,
      "value": 7117365,
      "optionType": "STOCK",
      "typeInfo": {
        "label": "Stock",
        "badge": "bg-blue-100 text-blue-800 border-blue-200",
        "strategy": "equity"
      },
      "titleOfClass": "COMMON STOCK",
      "putCall": null
    },
    {
      "name": "CLEAR SECURE INC",
      "cusip": "18467V109",
      "shares": 145900,
      "value": 7063019,
      "optionType": "STOCK",
      "typeInfo": {
        "label": "Stock",
        "badge": "bg-blue-100 text-blue-800 border-blue-200",
        "strategy": "equity"
      },
      "titleOfClass": "COM CL A",
      "putCall": null
    },
    {
      "name": "VANGUARD INDEX FDS",
      "cusip": "922908736",
      "shares": 16030,
      "value": 7001827,
      "optionType": "STOCK",
      "typeInfo": {
        "label": "Stock",
        "badge": "bg-blue-100 text-blue-800 border-blue-200",
        "strategy": "equity"
      },
      "titleOfClass": "GROWTH ETF",
      "putCall": null
    },
    {
      "name": "FASTLY INC",
      "cusip": "31188V100",
      "shares": 238518,
      "value": 6931333,
      "optionType": "STOCK",
      "typeInfo": {
        "label": "Stock",
        "badge": "bg-blue-100 text-blue-800 border-blue-200",
        "strategy": "equity"
      },
      "titleOfClass": "CL A",
      "putCall": null
    },
    {
      "name": "MODINE MFG CO",
      "cusip": "607828100",
      "shares": 29042,
      "value": 6293692,
      "optionType": "STOCK",
      "typeInfo": {
        "label": "Stock",
        "badge": "bg-blue-100 text-blue-800 border-blue-200",
        "strategy": "equity"
      },
      "titleOfClass": "COM",
      "putCall": null
    },
    {
      "name": "PLANET LABS PBC",
      "cusip": "72703X106",
      "shares": 213914,
      "value": 5978896,
      "optionType": "STOCK",
      "typeInfo": {
        "label": "Stock",
        "badge": "bg-blue-100 text-blue-800 border-blue-200",
        "strategy": "equity"
      },
      "titleOfClass": "COM CL A",
      "putCall": null
    },
    {
      "name": "DLOCAL LTD",
      "cusip": "G29018101",
      "shares": 458909,
      "value": 5952050,
      "optionType": "STOCK",
      "typeInfo": {
        "label": "Stock",
        "badge": "bg-blue-100 text-blue-800 border-blue-200",
        "strategy": "equity"
      },
      "titleOfClass": "CLASS A COM",
      "putCall": null
    },
    {
      "name": "BROOKDALE SR LIVING INC",
      "cusip": "112463104",
      "shares": 420374,
      "value": 5750716,
      "optionType": "STOCK",
      "typeInfo": {
        "label": "Stock",
        "badge": "bg-blue-100 text-blue-800 border-blue-200",
        "strategy": "equity"
      },
      "titleOfClass": "COM",
      "putCall": null
    },
    {
      "name": "IES HOLDINGS INC",
      "cusip": "44951W106",
      "shares": 11953,
      "value": 5695246,
      "optionType": "STOCK",
      "typeInfo": {
        "label": "Stock",
        "badge": "bg-blue-100 text-blue-800 border-blue-200",
        "strategy": "equity"
      },
      "titleOfClass": "COM",
      "putCall": null
    },
    {
      "name": "SPHERE ENTERTAINMENT CO",
      "cusip": "55826T102",
      "shares": 48293,
      "value": 5669598,
      "optionType": "STOCK",
      "typeInfo": {
        "label": "Stock",
        "badge": "bg-blue-100 text-blue-800 border-blue-200",
        "strategy": "equity"
      },
      "titleOfClass": "CL A",
      "putCall": null
    },
    {
      "name": "WILLIS TOWERS WATSON PLC LTD",
      "cusip": "G96629103",
      "shares": 19376,
      "value": 5632577,
      "optionType": "STOCK",
      "typeInfo": {
        "label": "Stock",
        "badge": "bg-blue-100 text-blue-800 border-blue-200",
        "strategy": "equity"
      },
      "titleOfClass": "SHS",
      "putCall": null
    },
    {
      "name": "ISHARES TR",
      "cusip": "46429B671",
      "shares": 96813,
      "value": 5438954,
      "optionType": "STOCK",
      "typeInfo": {
        "label": "Stock",
        "badge": "bg-blue-100 text-blue-800 border-blue-200",
        "strategy": "equity"
      },
      "titleOfClass": "MSCI CHINA ETF",
      "putCall": null
    },
    {
      "name": "MEDTRONIC PLC",
      "cusip": "G5960L103",
      "shares": 60661,
      "value": 5256201,
      "optionType": "STOCK",
      "typeInfo": {
        "label": "Stock",
        "badge": "bg-blue-100 text-blue-800 border-blue-200",
        "strategy": "equity"
      },
      "titleOfClass": "SHS",
      "putCall": null
    },
    {
      "name": "ISHARES INC",
      "cusip": "46434G772",
      "shares": 72894,
      "value": 5169642,
      "optionType": "STOCK",
      "typeInfo": {
        "label": "Stock",
        "badge": "bg-blue-100 text-blue-800 border-blue-200",
        "strategy": "equity"
      },
      "titleOfClass": "MSCI TAIWAN ETF",
      "putCall": null
    },
    {
      "name": "NLIGHT INC",
      "cusip": "65487K100",
      "shares": 89791,
      "value": 5119883,
      "optionType": "STOCK",
      "typeInfo": {
        "label": "Stock",
        "badge": "bg-blue-100 text-blue-800 border-blue-200",
        "strategy": "equity"
      },
      "titleOfClass": "COM",
      "putCall": null
    },
    {
      "name": "ASTRAZENECA PLC",
      "cusip": "G0593M107",
      "shares": 26046,
      "value": 5118898,
      "optionType": "STOCK",
      "typeInfo": {
        "label": "Stock",
        "badge": "bg-blue-100 text-blue-800 border-blue-200",
        "strategy": "equity"
      },
      "titleOfClass": "ORD",
      "putCall": null
    },
    {
      "name": "GENEDX HOLDINGS CORP",
      "cusip": "81663L200",
      "shares": 77419,
      "value": 4971848,
      "optionType": "STOCK",
      "typeInfo": {
        "label": "Stock",
        "badge": "bg-blue-100 text-blue-800 border-blue-200",
        "strategy": "equity"
      },
      "titleOfClass": "COM CL A",
      "putCall": null
    },
    {
      "name": "CARPENTER TECHNOLOGY CORP",
      "cusip": "144285103",
      "shares": 12431,
      "value": 4899679,
      "optionType": "STOCK",
      "typeInfo": {
        "label": "Stock",
        "badge": "bg-blue-100 text-blue-800 border-blue-200",
        "strategy": "equity"
      },
      "titleOfClass": "COM",
      "putCall": null
    },
    {
      "name": "SOLARIS ENERGY INFRAS INC",
      "cusip": "83418M103",
      "shares": 83675,
      "value": 4728474,
      "optionType": "STOCK",
      "typeInfo": {
        "label": "Stock",
        "badge": "bg-blue-100 text-blue-800 border-blue-200",
        "strategy": "equity"
      },
      "titleOfClass": "COM CL A",
      "putCall": null
    },
    {
      "name": "BABCOCK & WILCOX ENTERPRISES",
      "cusip": "05614L209",
      "shares": 271492,
      "value": 3988217,
      "optionType": "STOCK",
      "typeInfo": {
        "label": "Stock",
        "badge": "bg-blue-100 text-blue-800 border-blue-200",
        "strategy": "equity"
      },
      "titleOfClass": "COM",
      "putCall": null
    },
    {
      "name": "TENCENT MUSIC ENTMT GROUP",
      "cusip": "88034P109",
      "shares": 410278,
      "value": 3807380,
      "optionType": "STOCK",
      "typeInfo": {
        "label": "Stock",
        "badge": "bg-blue-100 text-blue-800 border-blue-200",
        "strategy": "equity"
      },
      "titleOfClass": "SPON ADS",
      "putCall": null
    },
    {
      "name": "PAYCOM SOFTWARE INC",
      "cusip": "70432V102",
      "shares": 30831,
      "value": 3747225,
      "optionType": "STOCK",
      "typeInfo": {
        "label": "Stock",
        "badge": "bg-blue-100 text-blue-800 border-blue-200",
        "strategy": "equity"
      },
      "titleOfClass": "COM",
      "putCall": null
    },
    {
      "name": "FIGURE TECHNOLOGY SOLUTIO",
      "cusip": "349381103",
      "shares": 105634,
      "value": 3586274,
      "optionType": "STOCK",
      "typeInfo": {
        "label": "Stock",
        "badge": "bg-blue-100 text-blue-800 border-blue-200",
        "strategy": "equity"
      },
      "titleOfClass": "COM CL A",
      "putCall": null
    },
    {
      "name": "KARMAN HLDGS INC",
      "cusip": "485924104",
      "shares": 44066,
      "value": 3527483,
      "optionType": "STOCK",
      "typeInfo": {
        "label": "Stock",
        "badge": "bg-blue-100 text-blue-800 border-blue-200",
        "strategy": "equity"
      },
      "titleOfClass": "COMMON STOCK",
      "putCall": null
    },
    {
      "name": "BRIDGEBIO PHARMA INC",
      "cusip": "10806X102",
      "shares": 45934,
      "value": 3411059,
      "optionType": "STOCK",
      "typeInfo": {
        "label": "Stock",
        "badge": "bg-blue-100 text-blue-800 border-blue-200",
        "strategy": "equity"
      },
      "titleOfClass": "COM",
      "putCall": null
    },
    {
      "name": "PRAXIS PRECISION MEDICINES I",
      "cusip": "74006W207",
      "shares": 10043,
      "value": 3235754,
      "optionType": "STOCK",
      "typeInfo": {
        "label": "Stock",
        "badge": "bg-blue-100 text-blue-800 border-blue-200",
        "strategy": "equity"
      },
      "titleOfClass": "COM NEW",
      "putCall": null
    },
    {
      "name": "GUARDANT HEALTH INC",
      "cusip": "40131M109",
      "shares": 34725,
      "value": 3207548,
      "optionType": "STOCK",
      "typeInfo": {
        "label": "Stock",
        "badge": "bg-blue-100 text-blue-800 border-blue-200",
        "strategy": "equity"
      },
      "titleOfClass": "COM",
      "putCall": null
    },
    {
      "name": "ICICI BANK LIMITED",
      "cusip": "45104G104",
      "shares": 118059,
      "value": 3057724,
      "optionType": "STOCK",
      "typeInfo": {
        "label": "Stock",
        "badge": "bg-blue-100 text-blue-800 border-blue-200",
        "strategy": "equity"
      },
      "titleOfClass": "ADR",
      "putCall": null
    },
    {
      "name": "ON HLDG AG",
      "cusip": "H5919C104",
      "shares": 88051,
      "value": 2995481,
      "optionType": "STOCK",
      "typeInfo": {
        "label": "Stock",
        "badge": "bg-blue-100 text-blue-800 border-blue-200",
        "strategy": "equity"
      },
      "titleOfClass": "NAMEN AKT A",
      "putCall": null
    },
    {
      "name": "AEHR TEST SYS",
      "cusip": "00760J108",
      "shares": 79396,
      "value": 2944004,
      "optionType": "STOCK",
      "typeInfo": {
        "label": "Stock",
        "badge": "bg-blue-100 text-blue-800 border-blue-200",
        "strategy": "equity"
      },
      "titleOfClass": "COM",
      "putCall": null
    },
    {
      "name": "CONSTRUCTION PARTNERS INC",
      "cusip": "21044C107",
      "shares": 26329,
      "value": 2925678,
      "optionType": "STOCK",
      "typeInfo": {
        "label": "Stock",
        "badge": "bg-blue-100 text-blue-800 border-blue-200",
        "strategy": "equity"
      },
      "titleOfClass": "COM CL A",
      "putCall": null
    },
    {
      "name": "ADOBE INC",
      "cusip": "00724F101",
      "shares": 11868,
      "value": 2884835,
      "optionType": "STOCK",
      "typeInfo": {
        "label": "Stock",
        "badge": "bg-blue-100 text-blue-800 border-blue-200",
        "strategy": "equity"
      },
      "titleOfClass": "COM",
      "putCall": null
    },
    {
      "name": "ASTRONICS CORP",
      "cusip": "046433108",
      "shares": 42410,
      "value": 2830019,
      "optionType": "STOCK",
      "typeInfo": {
        "label": "Stock",
        "badge": "bg-blue-100 text-blue-800 border-blue-200",
        "strategy": "equity"
      },
      "titleOfClass": "COM",
      "putCall": null
    },
    {
      "name": "AXT INC",
      "cusip": "00246W103",
      "shares": 49368,
      "value": 2812989,
      "optionType": "STOCK",
      "typeInfo": {
        "label": "Stock",
        "badge": "bg-blue-100 text-blue-800 border-blue-200",
        "strategy": "equity"
      },
      "titleOfClass": "COM",
      "putCall": null
    },
    {
      "name": "TESLA INC",
      "cusip": "88160R101",
      "shares": 7368,
      "value": 2739054,
      "optionType": "STOCK",
      "typeInfo": {
        "label": "Stock",
        "badge": "bg-blue-100 text-blue-800 border-blue-200",
        "strategy": "equity"
      },
      "titleOfClass": "COM",
      "putCall": null
    },
    {
      "name": "SEA LTD",
      "cusip": "81141R100",
      "shares": 32874,
      "value": 2722322,
      "optionType": "STOCK",
      "typeInfo": {
        "label": "Stock",
        "badge": "bg-blue-100 text-blue-800 border-blue-200",
        "strategy": "equity"
      },
      "titleOfClass": "SPONSORD ADS",
      "putCall": null
    },
    {
      "name": "MILLICOM INTL CELLULAR S A",
      "cusip": "L6388F110",
      "shares": 36096,
      "value": 2705034,
      "optionType": "STOCK",
      "typeInfo": {
        "label": "Stock",
        "badge": "bg-blue-100 text-blue-800 border-blue-200",
        "strategy": "equity"
      },
      "titleOfClass": "COM STK",
      "putCall": null
    },
    {
      "name": "CORPORACION AMER ARPTS S A",
      "cusip": "L1995B107",
      "shares": 106069,
      "value": 2682485,
      "optionType": "STOCK",
      "typeInfo": {
        "label": "Stock",
        "badge": "bg-blue-100 text-blue-800 border-blue-200",
        "strategy": "equity"
      },
      "titleOfClass": "COM",
      "putCall": null
    },
    {
      "name": "WAYFAIR INC",
      "cusip": "94419L101",
      "shares": 35216,
      "value": 2648595,
      "optionType": "STOCK",
      "typeInfo": {
        "label": "Stock",
        "badge": "bg-blue-100 text-blue-800 border-blue-200",
        "strategy": "equity"
      },
      "titleOfClass": "CL A",
      "putCall": null
    },
    {
      "name": "VICTORY CAP HLDGS INC DEL",
      "cusip": "92645B103",
      "shares": 39868,
      "value": 2610557,
      "optionType": "STOCK",
      "typeInfo": {
        "label": "Stock",
        "badge": "bg-blue-100 text-blue-800 border-blue-200",
        "strategy": "equity"
      },
      "titleOfClass": "COM CL A",
      "putCall": null
    },
    {
      "name": "PROTAGONIST THERAPEUTICS INC",
      "cusip": "74366E102",
      "shares": 24337,
      "value": 2565120,
      "optionType": "STOCK",
      "typeInfo": {
        "label": "Stock",
        "badge": "bg-blue-100 text-blue-800 border-blue-200",
        "strategy": "equity"
      },
      "titleOfClass": "COM",
      "putCall": null
    },
    {
      "name": "SCHOLAR ROCK HLDG CORP",
      "cusip": "80706P103",
      "shares": 51951,
      "value": 2553911,
      "optionType": "STOCK",
      "typeInfo": {
        "label": "Stock",
        "badge": "bg-blue-100 text-blue-800 border-blue-200",
        "strategy": "equity"
      },
      "titleOfClass": "COM",
      "putCall": null
    },
    {
      "name": "SITIME CORP",
      "cusip": "82982T106",
      "shares": 7101,
      "value": 2452330,
      "optionType": "STOCK",
      "typeInfo": {
        "label": "Stock",
        "badge": "bg-blue-100 text-blue-800 border-blue-200",
        "strategy": "equity"
      },
      "titleOfClass": "COM",
      "putCall": null
    },
    {
      "name": "STATE STR SPDR S&P 500 ETF T",
      "cusip": "78462F103",
      "shares": 3757,
      "value": 2443256,
      "optionType": "STOCK",
      "typeInfo": {
        "label": "Stock",
        "badge": "bg-blue-100 text-blue-800 border-blue-200",
        "strategy": "equity"
      },
      "titleOfClass": "TR UNIT",
      "putCall": null
    },
    {
      "name": "JOBY AVIATION INC",
      "cusip": "G65163100",
      "shares": 294754,
      "value": 2434668,
      "optionType": "STOCK",
      "typeInfo": {
        "label": "Stock",
        "badge": "bg-blue-100 text-blue-800 border-blue-200",
        "strategy": "equity"
      },
      "titleOfClass": "COMMON STOCK",
      "putCall": null
    },
    {
      "name": "OPPENHEIMER HLDGS INC",
      "cusip": "683797104",
      "shares": 26954,
      "value": 2404027,
      "optionType": "STOCK",
      "typeInfo": {
        "label": "Stock",
        "badge": "bg-blue-100 text-blue-800 border-blue-200",
        "strategy": "equity"
      },
      "titleOfClass": "CL A NON VTG",
      "putCall": null
    },
    {
      "name": "TECHNIPFMC PLC",
      "cusip": "G87110105",
      "shares": 34293,
      "value": 2370675,
      "optionType": "STOCK",
      "typeInfo": {
        "label": "Stock",
        "badge": "bg-blue-100 text-blue-800 border-blue-200",
        "strategy": "equity"
      },
      "titleOfClass": "COM",
      "putCall": null
    },
    {
      "name": "CARVANA CO",
      "cusip": "146869102",
      "shares": 7348,
      "value": 2310064,
      "optionType": "STOCK",
      "typeInfo": {
        "label": "Stock",
        "badge": "bg-blue-100 text-blue-800 border-blue-200",
        "strategy": "equity"
      },
      "titleOfClass": "CL A",
      "putCall": null
    },
    {
      "name": "VICOR CORP",
      "cusip": "925815102",
      "shares": 13899,
      "value": 2237739,
      "optionType": "STOCK",
      "typeInfo": {
        "label": "Stock",
        "badge": "bg-blue-100 text-blue-800 border-blue-200",
        "strategy": "equity"
      },
      "titleOfClass": "COM",
      "putCall": null
    },
    {
      "name": "RESOLUTE HLDGS MGMT INC",
      "cusip": "76134H101",
      "shares": 13669,
      "value": 2218479,
      "optionType": "STOCK",
      "typeInfo": {
        "label": "Stock",
        "badge": "bg-blue-100 text-blue-800 border-blue-200",
        "strategy": "equity"
      },
      "titleOfClass": "COM",
      "putCall": null
    },
    {
      "name": "ASTEC INDS INC",
      "cusip": "046224101",
      "shares": 41172,
      "value": 2216700,
      "optionType": "STOCK",
      "typeInfo": {
        "label": "Stock",
        "badge": "bg-blue-100 text-blue-800 border-blue-200",
        "strategy": "equity"
      },
      "titleOfClass": "COM",
      "putCall": null
    },
    {
      "name": "CAMECO CORP",
      "cusip": "13321L108",
      "shares": 20210,
      "value": 2195008,
      "optionType": "STOCK",
      "typeInfo": {
        "label": "Stock",
        "badge": "bg-blue-100 text-blue-800 border-blue-200",
        "strategy": "equity"
      },
      "titleOfClass": "COM",
      "putCall": null
    },
    {
      "name": "PROTO LABS INC",
      "cusip": "743713109",
      "shares": 37594,
      "value": 2143610,
      "optionType": "STOCK",
      "typeInfo": {
        "label": "Stock",
        "badge": "bg-blue-100 text-blue-800 border-blue-200",
        "strategy": "equity"
      },
      "titleOfClass": "COM",
      "putCall": null
    },
    {
      "name": "KRATOS DEFENSE & SEC SOLUTIO",
      "cusip": "50077B207",
      "shares": 29265,
      "value": 2063475,
      "optionType": "STOCK",
      "typeInfo": {
        "label": "Stock",
        "badge": "bg-blue-100 text-blue-800 border-blue-200",
        "strategy": "equity"
      },
      "titleOfClass": "COM NEW",
      "putCall": null
    },
    {
      "name": "THE REALREAL INC",
      "cusip": "88339P101",
      "shares": 221865,
      "value": 2014534,
      "optionType": "STOCK",
      "typeInfo": {
        "label": "Stock",
        "badge": "bg-blue-100 text-blue-800 border-blue-200",
        "strategy": "equity"
      },
      "titleOfClass": "COM",
      "putCall": null
    },
    {
      "name": "IRADIMED CORP",
      "cusip": "46266A109",
      "shares": 20744,
      "value": 1996817,
      "optionType": "STOCK",
      "typeInfo": {
        "label": "Stock",
        "badge": "bg-blue-100 text-blue-800 border-blue-200",
        "strategy": "equity"
      },
      "titleOfClass": "COM",
      "putCall": null
    },
    {
      "name": "PREFORMED LINE PRODS CO",
      "cusip": "740444104",
      "shares": 7341,
      "value": 1987576,
      "optionType": "STOCK",
      "typeInfo": {
        "label": "Stock",
        "badge": "bg-blue-100 text-blue-800 border-blue-200",
        "strategy": "equity"
      },
      "titleOfClass": "COM",
      "putCall": null
    },
    {
      "name": "CELCUITY INC",
      "cusip": "15102K100",
      "shares": 17181,
      "value": 1961039,
      "optionType": "STOCK",
      "typeInfo": {
        "label": "Stock",
        "badge": "bg-blue-100 text-blue-800 border-blue-200",
        "strategy": "equity"
      },
      "titleOfClass": "COM",
      "putCall": null
    },
    {
      "name": "MIRUM PHARMACEUTICALS INC",
      "cusip": "604749101",
      "shares": 20531,
      "value": 1896654,
      "optionType": "STOCK",
      "typeInfo": {
        "label": "Stock",
        "badge": "bg-blue-100 text-blue-800 border-blue-200",
        "strategy": "equity"
      },
      "titleOfClass": "COM",
      "putCall": null
    },
    {
      "name": "ERO COPPER CORP",
      "cusip": "296006109",
      "shares": 70159,
      "value": 1871141,
      "optionType": "STOCK",
      "typeInfo": {
        "label": "Stock",
        "badge": "bg-blue-100 text-blue-800 border-blue-200",
        "strategy": "equity"
      },
      "titleOfClass": "COM",
      "putCall": null
    },
    {
      "name": "RAMACO RES INC",
      "cusip": "75134P600",
      "shares": 119574,
      "value": 1848614,
      "optionType": "STOCK",
      "typeInfo": {
        "label": "Stock",
        "badge": "bg-blue-100 text-blue-800 border-blue-200",
        "strategy": "equity"
      },
      "titleOfClass": "COM CL A",
      "putCall": null
    },
    {
      "name": "AZZ INC",
      "cusip": "002474104",
      "shares": 14438,
      "value": 1806627,
      "optionType": "STOCK",
      "typeInfo": {
        "label": "Stock",
        "badge": "bg-blue-100 text-blue-800 border-blue-200",
        "strategy": "equity"
      },
      "titleOfClass": "COM",
      "putCall": null
    },
    {
      "name": "FIGS INC",
      "cusip": "30260D103",
      "shares": 121437,
      "value": 1793624,
      "optionType": "STOCK",
      "typeInfo": {
        "label": "Stock",
        "badge": "bg-blue-100 text-blue-800 border-blue-200",
        "strategy": "equity"
      },
      "titleOfClass": "CL A",
      "putCall": null
    },
    {
      "name": "AAR CORP",
      "cusip": "000361105",
      "shares": 16208,
      "value": 1774128,
      "optionType": "STOCK",
      "typeInfo": {
        "label": "Stock",
        "badge": "bg-blue-100 text-blue-800 border-blue-200",
        "strategy": "equity"
      },
      "titleOfClass": "COM",
      "putCall": null
    },
    {
      "name": "LINDBLAD EXPEDITIONS HLDGS I",
      "cusip": "535219109",
      "shares": 102127,
      "value": 1766797,
      "optionType": "STOCK",
      "typeInfo": {
        "label": "Stock",
        "badge": "bg-blue-100 text-blue-800 border-blue-200",
        "strategy": "equity"
      },
      "titleOfClass": "COM",
      "putCall": null
    },
    {
      "name": "ISHARES TR",
      "cusip": "464288240",
      "shares": 25676,
      "value": 1758012,
      "optionType": "STOCK",
      "typeInfo": {
        "label": "Stock",
        "badge": "bg-blue-100 text-blue-800 border-blue-200",
        "strategy": "equity"
      },
      "titleOfClass": "MSCI ACWI EX US",
      "putCall": null
    },
    {
      "name": "LITTELFUSE INC",
      "cusip": "537008104",
      "shares": 4959,
      "value": 1682837,
      "optionType": "STOCK",
      "typeInfo": {
        "label": "Stock",
        "badge": "bg-blue-100 text-blue-800 border-blue-200",
        "strategy": "equity"
      },
      "titleOfClass": "COM",
      "putCall": null
    },
    {
      "name": "SHAKE SHACK INC",
      "cusip": "819047101",
      "shares": 18840,
      "value": 1666775,
      "optionType": "STOCK",
      "typeInfo": {
        "label": "Stock",
        "badge": "bg-blue-100 text-blue-800 border-blue-200",
        "strategy": "equity"
      },
      "titleOfClass": "CL A",
      "putCall": null
    },
    {
      "name": "BUTTERFLY NETWORK INC",
      "cusip": "124155102",
      "shares": 406260,
      "value": 1641290,
      "optionType": "STOCK",
      "typeInfo": {
        "label": "Stock",
        "badge": "bg-blue-100 text-blue-800 border-blue-200",
        "strategy": "equity"
      },
      "titleOfClass": "COM CL A",
      "putCall": null
    },
    {
      "name": "SOFI TECHNOLOGIES INC",
      "cusip": "83406F102",
      "shares": 103345,
      "value": 1641119,
      "optionType": "STOCK",
      "typeInfo": {
        "label": "Stock",
        "badge": "bg-blue-100 text-blue-800 border-blue-200",
        "strategy": "equity"
      },
      "titleOfClass": "COM",
      "putCall": null
    },
    {
      "name": "ADAPTIVE BIOTECHNOLOGIES COR",
      "cusip": "00650F109",
      "shares": 116051,
      "value": 1610788,
      "optionType": "STOCK",
      "typeInfo": {
        "label": "Stock",
        "badge": "bg-blue-100 text-blue-800 border-blue-200",
        "strategy": "equity"
      },
      "titleOfClass": "COM",
      "putCall": null
    },
    {
      "name": "WISDOMTREE INC",
      "cusip": "97717P104",
      "shares": 109005,
      "value": 1587113,
      "optionType": "STOCK",
      "typeInfo": {
        "label": "Stock",
        "badge": "bg-blue-100 text-blue-800 border-blue-200",
        "strategy": "equity"
      },
      "titleOfClass": "COM",
      "putCall": null
    },
    {
      "name": "KODIAK SCIENCES INC",
      "cusip": "50015M109",
      "shares": 41354,
      "value": 1576414,
      "optionType": "STOCK",
      "typeInfo": {
        "label": "Stock",
        "badge": "bg-blue-100 text-blue-800 border-blue-200",
        "strategy": "equity"
      },
      "titleOfClass": "COM",
      "putCall": null
    },
    {
      "name": "ABBOTT LABORATORIES",
      "cusip": "002824100",
      "shares": 15081,
      "value": 1548326,
      "optionType": "STOCK",
      "typeInfo": {
        "label": "Stock",
        "badge": "bg-blue-100 text-blue-800 border-blue-200",
        "strategy": "equity"
      },
      "titleOfClass": "COM",
      "putCall": null
    },
    {
      "name": "TERAWULF INC",
      "cusip": "88080T104",
      "shares": 106375,
      "value": 1534991,
      "optionType": "STOCK",
      "typeInfo": {
        "label": "Stock",
        "badge": "bg-blue-100 text-blue-800 border-blue-200",
        "strategy": "equity"
      },
      "titleOfClass": "COM",
      "putCall": null
    },
    {
      "name": "IRSA INVERSIONES Y REP S A",
      "cusip": "450047303",
      "shares": 94136,
      "value": 1525945,
      "optionType": "STOCK",
      "typeInfo": {
        "label": "Stock",
        "badge": "bg-blue-100 text-blue-800 border-blue-200",
        "strategy": "equity"
      },
      "titleOfClass": "SPON GDS ECH 10",
      "putCall": null
    },
    {
      "name": "ROCKET LAB CORP",
      "cusip": "773121108",
      "shares": 23555,
      "value": 1512702,
      "optionType": "STOCK",
      "typeInfo": {
        "label": "Stock",
        "badge": "bg-blue-100 text-blue-800 border-blue-200",
        "strategy": "equity"
      },
      "titleOfClass": "COM",
      "putCall": null
    },
    {
      "name": "GLOBAL X FDS",
      "cusip": "37954Y889",
      "shares": 18868,
      "value": 1474534,
      "optionType": "STOCK",
      "typeInfo": {
        "label": "Stock",
        "badge": "bg-blue-100 text-blue-800 border-blue-200",
        "strategy": "equity"
      },
      "titleOfClass": "S&P 500 CATHOLIC",
      "putCall": null
    },
    {
      "name": "AXOS FINANCIAL INC",
      "cusip": "05465C100",
      "shares": 16849,
      "value": 1433681,
      "optionType": "STOCK",
      "typeInfo": {
        "label": "Stock",
        "badge": "bg-blue-100 text-blue-800 border-blue-200",
        "strategy": "equity"
      },
      "titleOfClass": "COM",
      "putCall": null
    },
    {
      "name": "TAYSHA GENE THERAPIES INC",
      "cusip": "877619106",
      "shares": 319748,
      "value": 1429274,
      "optionType": "STOCK",
      "typeInfo": {
        "label": "Stock",
        "badge": "bg-blue-100 text-blue-800 border-blue-200",
        "strategy": "equity"
      },
      "titleOfClass": "COM SHS",
      "putCall": null
    },
    {
      "name": "GRAHAM CORP",
      "cusip": "384556106",
      "shares": 17813,
      "value": 1405802,
      "optionType": "STOCK",
      "typeInfo": {
        "label": "Stock",
        "badge": "bg-blue-100 text-blue-800 border-blue-200",
        "strategy": "equity"
      },
      "titleOfClass": "COM",
      "putCall": null
    },
    {
      "name": "ESTABLISHMENT LABS HLDGS INC",
      "cusip": "G31249108",
      "shares": 24324,
      "value": 1381117,
      "optionType": "STOCK",
      "typeInfo": {
        "label": "Stock",
        "badge": "bg-blue-100 text-blue-800 border-blue-200",
        "strategy": "equity"
      },
      "titleOfClass": "COM",
      "putCall": null
    },
    {
      "name": "NEXGEN ENERGY LTD",
      "cusip": "65340P106",
      "shares": 117610,
      "value": 1364276,
      "optionType": "STOCK",
      "typeInfo": {
        "label": "Stock",
        "badge": "bg-blue-100 text-blue-800 border-blue-200",
        "strategy": "equity"
      },
      "titleOfClass": "COM",
      "putCall": null
    },
    {
      "name": "OUTFRONT MEDIA INC",
      "cusip": "69007J304",
      "shares": 51411,
      "value": 1362392,
      "optionType": "STOCK",
      "typeInfo": {
        "label": "Stock",
        "badge": "bg-blue-100 text-blue-800 border-blue-200",
        "strategy": "equity"
      },
      "titleOfClass": "COM NEW",
      "putCall": null
    },
    {
      "name": "CHEESECAKE FACTORY INC",
      "cusip": "163072101",
      "shares": 24822,
      "value": 1359005,
      "optionType": "STOCK",
      "typeInfo": {
        "label": "Stock",
        "badge": "bg-blue-100 text-blue-800 border-blue-200",
        "strategy": "equity"
      },
      "titleOfClass": "COM",
      "putCall": null
    },
    {
      "name": "NUVALENT INC",
      "cusip": "670703107",
      "shares": 12744,
      "value": 1305623,
      "optionType": "STOCK",
      "typeInfo": {
        "label": "Stock",
        "badge": "bg-blue-100 text-blue-800 border-blue-200",
        "strategy": "equity"
      },
      "titleOfClass": "COM",
      "putCall": null
    },
    {
      "name": "APPLIED OPTOELECTRONICS INC",
      "cusip": "03823U102",
      "shares": 14913,
      "value": 1261491,
      "optionType": "STOCK",
      "typeInfo": {
        "label": "Stock",
        "badge": "bg-blue-100 text-blue-800 border-blue-200",
        "strategy": "equity"
      },
      "titleOfClass": "COM",
      "putCall": null
    },
    {
      "name": "ESQUIRE FINL HLDGS INC",
      "cusip": "29667J101",
      "shares": 11713,
      "value": 1259148,
      "optionType": "STOCK",
      "typeInfo": {
        "label": "Stock",
        "badge": "bg-blue-100 text-blue-800 border-blue-200",
        "strategy": "equity"
      },
      "titleOfClass": "COM",
      "putCall": null
    },
    {
      "name": "DENALI THERAPEUTICS INC",
      "cusip": "24823R105",
      "shares": 65301,
      "value": 1253779,
      "optionType": "STOCK",
      "typeInfo": {
        "label": "Stock",
        "badge": "bg-blue-100 text-blue-800 border-blue-200",
        "strategy": "equity"
      },
      "titleOfClass": "COM",
      "putCall": null
    },
    {
      "name": "CIRCLE INTERNET GROUP INC",
      "cusip": "172573107",
      "shares": 13098,
      "value": 1249680,
      "optionType": "STOCK",
      "typeInfo": {
        "label": "Stock",
        "badge": "bg-blue-100 text-blue-800 border-blue-200",
        "strategy": "equity"
      },
      "titleOfClass": "COM CL A",
      "putCall": null
    },
    {
      "name": "IONQ INC",
      "cusip": "46222L108",
      "shares": 42109,
      "value": 1214002,
      "optionType": "STOCK",
      "typeInfo": {
        "label": "Stock",
        "badge": "bg-blue-100 text-blue-800 border-blue-200",
        "strategy": "equity"
      },
      "titleOfClass": "COM",
      "putCall": null
    },
    {
      "name": "IVANHOE ELECTRIC INC",
      "cusip": "46578C108",
      "shares": 97186,
      "value": 1148739,
      "optionType": "STOCK",
      "typeInfo": {
        "label": "Stock",
        "badge": "bg-blue-100 text-blue-800 border-blue-200",
        "strategy": "equity"
      },
      "titleOfClass": "COM",
      "putCall": null
    },
    {
      "name": "TWIST BIOSCIENCE CORP",
      "cusip": "90184D100",
      "shares": 24037,
      "value": 1142238,
      "optionType": "STOCK",
      "typeInfo": {
        "label": "Stock",
        "badge": "bg-blue-100 text-blue-800 border-blue-200",
        "strategy": "equity"
      },
      "titleOfClass": "COM",
      "putCall": null
    },
    {
      "name": "ISHARES TR",
      "cusip": "46436E718",
      "shares": 11267,
      "value": 1134136,
      "optionType": "STOCK",
      "typeInfo": {
        "label": "Stock",
        "badge": "bg-blue-100 text-blue-800 border-blue-200",
        "strategy": "equity"
      },
      "titleOfClass": "0-3 MNTH TREASRY",
      "putCall": null
    },
    {
      "name": "LIFE TIME GROUP HOLDINGS INC",
      "cusip": "53190C102",
      "shares": 40481,
      "value": 1090558,
      "optionType": "STOCK",
      "typeInfo": {
        "label": "Stock",
        "badge": "bg-blue-100 text-blue-800 border-blue-200",
        "strategy": "equity"
      },
      "titleOfClass": "COMMON STOCK",
      "putCall": null
    },
    {
      "name": "SIONNA THERAPEUTICS INC",
      "cusip": "829401108",
      "shares": 26775,
      "value": 1073410,
      "optionType": "STOCK",
      "typeInfo": {
        "label": "Stock",
        "badge": "bg-blue-100 text-blue-800 border-blue-200",
        "strategy": "equity"
      },
      "titleOfClass": "COM",
      "putCall": null
    },
    {
      "name": "VISHAY PRECISION GROUP INC",
      "cusip": "92835K103",
      "shares": 24263,
      "value": 1053499,
      "optionType": "STOCK",
      "typeInfo": {
        "label": "Stock",
        "badge": "bg-blue-100 text-blue-800 border-blue-200",
        "strategy": "equity"
      },
      "titleOfClass": "COM",
      "putCall": null
    },
    {
      "name": "STERLING INFRASTRUCTURE INC",
      "cusip": "859241101",
      "shares": 2553,
      "value": 1039760,
      "optionType": "STOCK",
      "typeInfo": {
        "label": "Stock",
        "badge": "bg-blue-100 text-blue-800 border-blue-200",
        "strategy": "equity"
      },
      "titleOfClass": "COM",
      "putCall": null
    },
    {
      "name": "CENTRAL PAC FINL CORP",
      "cusip": "154760409",
      "shares": 32323,
      "value": 1033043,
      "optionType": "STOCK",
      "typeInfo": {
        "label": "Stock",
        "badge": "bg-blue-100 text-blue-800 border-blue-200",
        "strategy": "equity"
      },
      "titleOfClass": "COM NEW",
      "putCall": null
    },
    {
      "name": "APPLE INC",
      "cusip": "037833100",
      "shares": 4052,
      "value": 1028389,
      "optionType": "STOCK",
      "typeInfo": {
        "label": "Stock",
        "badge": "bg-blue-100 text-blue-800 border-blue-200",
        "strategy": "equity"
      },
      "titleOfClass": "COM",
      "putCall": null
    },
    {
      "name": "FABRINET",
      "cusip": "G3323L100",
      "shares": 1930,
      "value": 1006534,
      "optionType": "STOCK",
      "typeInfo": {
        "label": "Stock",
        "badge": "bg-blue-100 text-blue-800 border-blue-200",
        "strategy": "equity"
      },
      "titleOfClass": "SHS",
      "putCall": null
    },
    {
      "name": "MAMAS CREATIONS INC",
      "cusip": "56146T103",
      "shares": 65408,
      "value": 1003359,
      "optionType": "STOCK",
      "typeInfo": {
        "label": "Stock",
        "badge": "bg-blue-100 text-blue-800 border-blue-200",
        "strategy": "equity"
      },
      "titleOfClass": "COM",
      "putCall": null
    },
    {
      "name": "XOMETRY INC",
      "cusip": "98423F109",
      "shares": 24564,
      "value": 1003194,
      "optionType": "STOCK",
      "typeInfo": {
        "label": "Stock",
        "badge": "bg-blue-100 text-blue-800 border-blue-200",
        "strategy": "equity"
      },
      "titleOfClass": "CLASS A COM",
      "putCall": null
    },
    {
      "name": "FLUOR CORP",
      "cusip": "343412102",
      "shares": 21011,
      "value": 980163,
      "optionType": "STOCK",
      "typeInfo": {
        "label": "Stock",
        "badge": "bg-blue-100 text-blue-800 border-blue-200",
        "strategy": "equity"
      },
      "titleOfClass": "COM",
      "putCall": null
    },
    {
      "name": "CALLAWAY GOLF CO",
      "cusip": "131193104",
      "shares": 70431,
      "value": 977582,
      "optionType": "STOCK",
      "typeInfo": {
        "label": "Stock",
        "badge": "bg-blue-100 text-blue-800 border-blue-200",
        "strategy": "equity"
      },
      "titleOfClass": "COM",
      "putCall": null
    },
    {
      "name": "WINMARK CORP",
      "cusip": "974250102",
      "shares": 2283,
      "value": 976097,
      "optionType": "STOCK",
      "typeInfo": {
        "label": "Stock",
        "badge": "bg-blue-100 text-blue-800 border-blue-200",
        "strategy": "equity"
      },
      "titleOfClass": "COM",
      "putCall": null
    },
    {
      "name": "OPENLANE INC",
      "cusip": "48238T109",
      "shares": 33361,
      "value": 972473,
      "optionType": "STOCK",
      "typeInfo": {
        "label": "Stock",
        "badge": "bg-blue-100 text-blue-800 border-blue-200",
        "strategy": "equity"
      },
      "titleOfClass": "COM",
      "putCall": null
    },
    {
      "name": "ADTRAN HOLDINGS INC",
      "cusip": "00486H105",
      "shares": 75688,
      "value": 952155,
      "optionType": "STOCK",
      "typeInfo": {
        "label": "Stock",
        "badge": "bg-blue-100 text-blue-800 border-blue-200",
        "strategy": "equity"
      },
      "titleOfClass": "COM",
      "putCall": null
    },
    {
      "name": "JFROG LTD",
      "cusip": "M6191J100",
      "shares": 20240,
      "value": 949863,
      "optionType": "STOCK",
      "typeInfo": {
        "label": "Stock",
        "badge": "bg-blue-100 text-blue-800 border-blue-200",
        "strategy": "equity"
      },
      "titleOfClass": "ORD SHS",
      "putCall": null
    },
    {
      "name": "HCI GROUP INC",
      "cusip": "40416E103",
      "shares": 6106,
      "value": 944049,
      "optionType": "STOCK",
      "typeInfo": {
        "label": "Stock",
        "badge": "bg-blue-100 text-blue-800 border-blue-200",
        "strategy": "equity"
      },
      "titleOfClass": "COM",
      "putCall": null
    },
    {
      "name": "STRIDE INC",
      "cusip": "86333M108",
      "shares": 10571,
      "value": 932045,
      "optionType": "STOCK",
      "typeInfo": {
        "label": "Stock",
        "badge": "bg-blue-100 text-blue-800 border-blue-200",
        "strategy": "equity"
      },
      "titleOfClass": "COM",
      "putCall": null
    },
    {
      "name": "KONTOOR BRANDS INC",
      "cusip": "50050N103",
      "shares": 13192,
      "value": 927266,
      "optionType": "STOCK",
      "typeInfo": {
        "label": "Stock",
        "badge": "bg-blue-100 text-blue-800 border-blue-200",
        "strategy": "equity"
      },
      "titleOfClass": "COM",
      "putCall": null
    },
    {
      "name": "VANGUARD INTL EQUITY INDEX F",
      "cusip": "922042742",
      "shares": 6600,
      "value": 912950,
      "optionType": "STOCK",
      "typeInfo": {
        "label": "Stock",
        "badge": "bg-blue-100 text-blue-800 border-blue-200",
        "strategy": "equity"
      },
      "titleOfClass": "TT WRLD ST ETF",
      "putCall": null
    },
    {
      "name": "CANTOR EQUITY PARTNERS II IN",
      "cusip": "G1827P106",
      "shares": 82865,
      "value": 902400,
      "optionType": "STOCK",
      "typeInfo": {
        "label": "Stock",
        "badge": "bg-blue-100 text-blue-800 border-blue-200",
        "strategy": "equity"
      },
      "titleOfClass": "CL A ORD SHS",
      "putCall": null
    },
    {
      "name": "GREEN BRICK PARTNERS INC",
      "cusip": "392709101",
      "shares": 13184,
      "value": 849709,
      "optionType": "STOCK",
      "typeInfo": {
        "label": "Stock",
        "badge": "bg-blue-100 text-blue-800 border-blue-200",
        "strategy": "equity"
      },
      "titleOfClass": "COM",
      "putCall": null
    },
    {
      "name": "ARLO TECHNOLOGIES INC",
      "cusip": "04206A101",
      "shares": 58674,
      "value": 834931,
      "optionType": "STOCK",
      "typeInfo": {
        "label": "Stock",
        "badge": "bg-blue-100 text-blue-800 border-blue-200",
        "strategy": "equity"
      },
      "titleOfClass": "COM",
      "putCall": null
    },
    {
      "name": "CURTISS WRIGHT CORP",
      "cusip": "231561101",
      "shares": 1192,
      "value": 811895,
      "optionType": "STOCK",
      "typeInfo": {
        "label": "Stock",
        "badge": "bg-blue-100 text-blue-800 border-blue-200",
        "strategy": "equity"
      },
      "titleOfClass": "COM",
      "putCall": null
    },
    {
      "name": "AMERICAN PUB ED INC",
      "cusip": "02913V103",
      "shares": 14122,
      "value": 803259,
      "optionType": "STOCK",
      "typeInfo": {
        "label": "Stock",
        "badge": "bg-blue-100 text-blue-800 border-blue-200",
        "strategy": "equity"
      },
      "titleOfClass": "COM",
      "putCall": null
    },
    {
      "name": "LIGHTPATH TECHNOLOGIES INC",
      "cusip": "532257805",
      "shares": 79055,
      "value": 792922,
      "optionType": "STOCK",
      "typeInfo": {
        "label": "Stock",
        "badge": "bg-blue-100 text-blue-800 border-blue-200",
        "strategy": "equity"
      },
      "titleOfClass": "COM CL A",
      "putCall": null
    },
    {
      "name": "BLACKSKY TECHNOLOGY INC",
      "cusip": "09263B207",
      "shares": 30642,
      "value": 770953,
      "optionType": "STOCK",
      "typeInfo": {
        "label": "Stock",
        "badge": "bg-blue-100 text-blue-800 border-blue-200",
        "strategy": "equity"
      },
      "titleOfClass": "CL A NEW",
      "putCall": null
    },
    {
      "name": "ETON PHARMACEUTICALS INC",
      "cusip": "29772L108",
      "shares": 30138,
      "value": 743806,
      "optionType": "STOCK",
      "typeInfo": {
        "label": "Stock",
        "badge": "bg-blue-100 text-blue-800 border-blue-200",
        "strategy": "equity"
      },
      "titleOfClass": "COM",
      "putCall": null
    },
    {
      "name": "TRANSMEDICS GROUP INC",
      "cusip": "89377M109",
      "shares": 7422,
      "value": 737821,
      "optionType": "STOCK",
      "typeInfo": {
        "label": "Stock",
        "badge": "bg-blue-100 text-blue-800 border-blue-200",
        "strategy": "equity"
      },
      "titleOfClass": "COM",
      "putCall": null
    },
    {
      "name": "FIREFLY AEROSPACE INC",
      "cusip": "31816X106",
      "shares": 25499,
      "value": 725957,
      "optionType": "STOCK",
      "typeInfo": {
        "label": "Stock",
        "badge": "bg-blue-100 text-blue-800 border-blue-200",
        "strategy": "equity"
      },
      "titleOfClass": "COM",
      "putCall": null
    },
    {
      "name": "DAVE INC",
      "cusip": "23834J201",
      "shares": 3869,
      "value": 673554,
      "optionType": "STOCK",
      "typeInfo": {
        "label": "Stock",
        "badge": "bg-blue-100 text-blue-800 border-blue-200",
        "strategy": "equity"
      },
      "titleOfClass": "CLASS A COM NEW",
      "putCall": null
    },
    {
      "name": "ONCE UPON A FARM PBC",
      "cusip": "68237F108",
      "shares": 40631,
      "value": 664317,
      "optionType": "STOCK",
      "typeInfo": {
        "label": "Stock",
        "badge": "bg-blue-100 text-blue-800 border-blue-200",
        "strategy": "equity"
      },
      "titleOfClass": "COM",
      "putCall": null
    },
    {
      "name": "HDFC BANK LTD",
      "cusip": "40415F101",
      "shares": 23926,
      "value": 595289,
      "optionType": "STOCK",
      "typeInfo": {
        "label": "Stock",
        "badge": "bg-blue-100 text-blue-800 border-blue-200",
        "strategy": "equity"
      },
      "titleOfClass": "SPONSORED ADS",
      "putCall": null
    },
    {
      "name": "VELO3D INC",
      "cusip": "92259N302",
      "shares": 61433,
      "value": 576856,
      "optionType": "STOCK",
      "typeInfo": {
        "label": "Stock",
        "badge": "bg-blue-100 text-blue-800 border-blue-200",
        "strategy": "equity"
      },
      "titleOfClass": "COM NEW",
      "putCall": null
    },
    {
      "name": "GPGI INC",
      "cusip": "20459V105",
      "shares": 33406,
      "value": 571243,
      "optionType": "STOCK",
      "typeInfo": {
        "label": "Stock",
        "badge": "bg-blue-100 text-blue-800 border-blue-200",
        "strategy": "equity"
      },
      "titleOfClass": "COM CL A",
      "putCall": null
    },
    {
      "name": "BETTER HOME & FINANCE HOLDIN",
      "cusip": "08774B508",
      "shares": 15959,
      "value": 568460,
      "optionType": "STOCK",
      "typeInfo": {
        "label": "Stock",
        "badge": "bg-blue-100 text-blue-800 border-blue-200",
        "strategy": "equity"
      },
      "titleOfClass": "COM NEW CL A",
      "putCall": null
    },
    {
      "name": "ASP ISOTOPES INC",
      "cusip": "00218A105",
      "shares": 122970,
      "value": 543527,
      "optionType": "STOCK",
      "typeInfo": {
        "label": "Stock",
        "badge": "bg-blue-100 text-blue-800 border-blue-200",
        "strategy": "equity"
      },
      "titleOfClass": "COM",
      "putCall": null
    },
    {
      "name": "EMBRAER S.A.",
      "cusip": "29082A107",
      "shares": 9138,
      "value": 542249,
      "optionType": "STOCK",
      "typeInfo": {
        "label": "Stock",
        "badge": "bg-blue-100 text-blue-800 border-blue-200",
        "strategy": "equity"
      },
      "titleOfClass": "SPONSORED ADS",
      "putCall": null
    },
    {
      "name": "ORION GROUP HLDGS INC",
      "cusip": "68628V308",
      "shares": 49265,
      "value": 536989,
      "optionType": "STOCK",
      "typeInfo": {
        "label": "Stock",
        "badge": "bg-blue-100 text-blue-800 border-blue-200",
        "strategy": "equity"
      },
      "titleOfClass": "COM",
      "putCall": null
    },
    {
      "name": "LEMONADE INC",
      "cusip": "52567D107",
      "shares": 8219,
      "value": 515167,
      "optionType": "STOCK",
      "typeInfo": {
        "label": "Stock",
        "badge": "bg-blue-100 text-blue-800 border-blue-200",
        "strategy": "equity"
      },
      "titleOfClass": "COM",
      "putCall": null
    },
    {
      "name": "SEMTECH CORP",
      "cusip": "816850101",
      "shares": 6553,
      "value": 503860,
      "optionType": "STOCK",
      "typeInfo": {
        "label": "Stock",
        "badge": "bg-blue-100 text-blue-800 border-blue-200",
        "strategy": "equity"
      },
      "titleOfClass": "COM",
      "putCall": null
    },
    {
      "name": "ANI PHARMACEUTICALS INC",
      "cusip": "00182C103",
      "shares": 6409,
      "value": 492852,
      "optionType": "STOCK",
      "typeInfo": {
        "label": "Stock",
        "badge": "bg-blue-100 text-blue-800 border-blue-200",
        "strategy": "equity"
      },
      "titleOfClass": "COM",
      "putCall": null
    },
    {
      "name": "THERMON GROUP HLDGS INC",
      "cusip": "88362T103",
      "shares": 9466,
      "value": 477086,
      "optionType": "STOCK",
      "typeInfo": {
        "label": "Stock",
        "badge": "bg-blue-100 text-blue-800 border-blue-200",
        "strategy": "equity"
      },
      "titleOfClass": "COM",
      "putCall": null
    },
    {
      "name": "FLOTEK INDUSTRIES INC",
      "cusip": "343389409",
      "shares": 27642,
      "value": 469085,
      "optionType": "STOCK",
      "typeInfo": {
        "label": "Stock",
        "badge": "bg-blue-100 text-blue-800 border-blue-200",
        "strategy": "equity"
      },
      "titleOfClass": "COM NEW",
      "putCall": null
    },
    {
      "name": "MANITOWOC CO INC",
      "cusip": "563571405",
      "shares": 39879,
      "value": 464590,
      "optionType": "STOCK",
      "typeInfo": {
        "label": "Stock",
        "badge": "bg-blue-100 text-blue-800 border-blue-200",
        "strategy": "equity"
      },
      "titleOfClass": "COM NEW",
      "putCall": null
    },
    {
      "name": "MIRION TECHNOLOGIES INC",
      "cusip": "60471A101",
      "shares": 24921,
      "value": 463281,
      "optionType": "STOCK",
      "typeInfo": {
        "label": "Stock",
        "badge": "bg-blue-100 text-blue-800 border-blue-200",
        "strategy": "equity"
      },
      "titleOfClass": "COM CL A",
      "putCall": null
    },
    {
      "name": "FTAI AVIATION LTD",
      "cusip": "G3730V105",
      "shares": 1762,
      "value": 431690,
      "optionType": "STOCK",
      "typeInfo": {
        "label": "Stock",
        "badge": "bg-blue-100 text-blue-800 border-blue-200",
        "strategy": "equity"
      },
      "titleOfClass": "SHS",
      "putCall": null
    },
    {
      "name": "ASCENDIS PHARMA A/S",
      "cusip": "04351P101",
      "shares": 1812,
      "value": 414459,
      "optionType": "STOCK",
      "typeInfo": {
        "label": "Stock",
        "badge": "bg-blue-100 text-blue-800 border-blue-200",
        "strategy": "equity"
      },
      "titleOfClass": "SPONSORED ADR",
      "putCall": null
    },
    {
      "name": "CLEAR CHANNEL OUTDOOR HLDGS",
      "cusip": "18453H106",
      "shares": 174708,
      "value": 414058,
      "optionType": "STOCK",
      "typeInfo": {
        "label": "Stock",
        "badge": "bg-blue-100 text-blue-800 border-blue-200",
        "strategy": "equity"
      },
      "titleOfClass": "COM",
      "putCall": null
    },
    {
      "name": "VEECO INSTRS INC DEL",
      "cusip": "922417100",
      "shares": 12028,
      "value": 407268,
      "optionType": "STOCK",
      "typeInfo": {
        "label": "Stock",
        "badge": "bg-blue-100 text-blue-800 border-blue-200",
        "strategy": "equity"
      },
      "titleOfClass": "COM",
      "putCall": null
    },
    {
      "name": "DELUXE CORP MEDIUM TERM NTS",
      "cusip": "248019101",
      "shares": 14157,
      "value": 389884,
      "optionType": "STOCK",
      "typeInfo": {
        "label": "Stock",
        "badge": "bg-blue-100 text-blue-800 border-blue-200",
        "strategy": "equity"
      },
      "titleOfClass": "COM",
      "putCall": null
    },
    {
      "name": "ANNEXON INC",
      "cusip": "03589W102",
      "shares": 70152,
      "value": 388642,
      "optionType": "STOCK",
      "typeInfo": {
        "label": "Stock",
        "badge": "bg-blue-100 text-blue-800 border-blue-200",
        "strategy": "equity"
      },
      "titleOfClass": "COM",
      "putCall": null
    },
    {
      "name": "MILLERKNOLL INC",
      "cusip": "600544100",
      "shares": 26305,
      "value": 380370,
      "optionType": "STOCK",
      "typeInfo": {
        "label": "Stock",
        "badge": "bg-blue-100 text-blue-800 border-blue-200",
        "strategy": "equity"
      },
      "titleOfClass": "COM",
      "putCall": null
    },
    {
      "name": "PHIBRO ANIMAL HEALTH CORP",
      "cusip": "71742Q106",
      "shares": 6775,
      "value": 374725,
      "optionType": "STOCK",
      "typeInfo": {
        "label": "Stock",
        "badge": "bg-blue-100 text-blue-800 border-blue-200",
        "strategy": "equity"
      },
      "titleOfClass": "CL A COM",
      "putCall": null
    },
    {
      "name": "ALTO NEUROSCIENCE INC",
      "cusip": "02157Q109",
      "shares": 16613,
      "value": 373460,
      "optionType": "STOCK",
      "typeInfo": {
        "label": "Stock",
        "badge": "bg-blue-100 text-blue-800 border-blue-200",
        "strategy": "equity"
      },
      "titleOfClass": "COM SHS",
      "putCall": null
    },
    {
      "name": "CENTRAL PUERTO S A",
      "cusip": "155038201",
      "shares": 22120,
      "value": 372280,
      "optionType": "STOCK",
      "typeInfo": {
        "label": "Stock",
        "badge": "bg-blue-100 text-blue-800 border-blue-200",
        "strategy": "equity"
      },
      "titleOfClass": "SPONSORED ADR",
      "putCall": null
    },
    {
      "name": "AXSOME THERAPEUTICS INC",
      "cusip": "05464T104",
      "shares": 2116,
      "value": 357646,
      "optionType": "STOCK",
      "typeInfo": {
        "label": "Stock",
        "badge": "bg-blue-100 text-blue-800 border-blue-200",
        "strategy": "equity"
      },
      "titleOfClass": "COM",
      "putCall": null
    },
    {
      "name": "MITEK SYS INC",
      "cusip": "606710200",
      "shares": 26445,
      "value": 357008,
      "optionType": "STOCK",
      "typeInfo": {
        "label": "Stock",
        "badge": "bg-blue-100 text-blue-800 border-blue-200",
        "strategy": "equity"
      },
      "titleOfClass": "COM NEW",
      "putCall": null
    },
    {
      "name": "BRISTOW GROUP INC",
      "cusip": "11040G103",
      "shares": 7483,
      "value": 350878,
      "optionType": "STOCK",
      "typeInfo": {
        "label": "Stock",
        "badge": "bg-blue-100 text-blue-800 border-blue-200",
        "strategy": "equity"
      },
      "titleOfClass": "COM",
      "putCall": null
    },
    {
      "name": "SKYWATER TECHNOLOGY INC",
      "cusip": "83089J108",
      "shares": 12715,
      "value": 348518,
      "optionType": "STOCK",
      "typeInfo": {
        "label": "Stock",
        "badge": "bg-blue-100 text-blue-800 border-blue-200",
        "strategy": "equity"
      },
      "titleOfClass": "COM",
      "putCall": null
    },
    {
      "name": "DIANTHUS THERAPEUTICS INC",
      "cusip": "252828108",
      "shares": 4119,
      "value": 345666,
      "optionType": "STOCK",
      "typeInfo": {
        "label": "Stock",
        "badge": "bg-blue-100 text-blue-800 border-blue-200",
        "strategy": "equity"
      },
      "titleOfClass": "COM",
      "putCall": null
    },
    {
      "name": "TWILIO INC",
      "cusip": "90138F102",
      "shares": 2708,
      "value": 340721,
      "optionType": "STOCK",
      "typeInfo": {
        "label": "Stock",
        "badge": "bg-blue-100 text-blue-800 border-blue-200",
        "strategy": "equity"
      },
      "titleOfClass": "CL A",
      "putCall": null
    },
    {
      "name": "ALCOA CORP",
      "cusip": "013872106",
      "shares": 4975,
      "value": 329992,
      "optionType": "STOCK",
      "typeInfo": {
        "label": "Stock",
        "badge": "bg-blue-100 text-blue-800 border-blue-200",
        "strategy": "equity"
      },
      "titleOfClass": "COM",
      "putCall": null
    },
    {
      "name": "HYPERLIQUID STRATEGIES INC",
      "cusip": "44916Y106",
      "shares": 62008,
      "value": 315621,
      "optionType": "STOCK",
      "typeInfo": {
        "label": "Stock",
        "badge": "bg-blue-100 text-blue-800 border-blue-200",
        "strategy": "equity"
      },
      "titleOfClass": "COM",
      "putCall": null
    },
    {
      "name": "SES AI CORPORATION",
      "cusip": "78397Q109",
      "shares": 320271,
      "value": 308101,
      "optionType": "STOCK",
      "typeInfo": {
        "label": "Stock",
        "badge": "bg-blue-100 text-blue-800 border-blue-200",
        "strategy": "equity"
      },
      "titleOfClass": "CL A COM",
      "putCall": null
    },
    {
      "name": "MUELLER INDS INC",
      "cusip": "624756102",
      "shares": 2769,
      "value": 306805,
      "optionType": "STOCK",
      "typeInfo": {
        "label": "Stock",
        "badge": "bg-blue-100 text-blue-800 border-blue-200",
        "strategy": "equity"
      },
      "titleOfClass": "COM",
      "putCall": null
    },
    {
      "name": "SANDISK CORP",
      "cusip": "80004C200",
      "shares": 453,
      "value": 287809,
      "optionType": "STOCK",
      "typeInfo": {
        "label": "Stock",
        "badge": "bg-blue-100 text-blue-800 border-blue-200",
        "strategy": "equity"
      },
      "titleOfClass": "COM",
      "putCall": null
    },
    {
      "name": "SHARKNINJA INC",
      "cusip": "G8068L108",
      "shares": 2491,
      "value": 263797,
      "optionType": "STOCK",
      "typeInfo": {
        "label": "Stock",
        "badge": "bg-blue-100 text-blue-800 border-blue-200",
        "strategy": "equity"
      },
      "titleOfClass": "COM SHS",
      "putCall": null
    },
    {
      "name": "NATERA INC",
      "cusip": "632307104",
      "shares": 1269,
      "value": 253787,
      "optionType": "STOCK",
      "typeInfo": {
        "label": "Stock",
        "badge": "bg-blue-100 text-blue-800 border-blue-200",
        "strategy": "equity"
      },
      "titleOfClass": "COM",
      "putCall": null
    },
    {
      "name": "FIRST SOLAR INC",
      "cusip": "336433107",
      "shares": 1275,
      "value": 251507,
      "optionType": "STOCK",
      "typeInfo": {
        "label": "Stock",
        "badge": "bg-blue-100 text-blue-800 border-blue-200",
        "strategy": "equity"
      },
      "titleOfClass": "COM",
      "putCall": null
    },
    {
      "name": "GARTNER INC",
      "cusip": "366651107",
      "shares": 1549,
      "value": 245280,
      "optionType": "STOCK",
      "typeInfo": {
        "label": "Stock",
        "badge": "bg-blue-100 text-blue-800 border-blue-200",
        "strategy": "equity"
      },
      "titleOfClass": "COM",
      "putCall": null
    },
    {
      "name": "VISTA ENERGY S.A.B. DE C.V.",
      "cusip": "92837L109",
      "shares": 3214,
      "value": 242561,
      "optionType": "STOCK",
      "typeInfo": {
        "label": "Stock",
        "badge": "bg-blue-100 text-blue-800 border-blue-200",
        "strategy": "equity"
      },
      "titleOfClass": "SPONSORED ADS",
      "putCall": null
    },
    {
      "name": "MACOM TECH SOLUTIONS HLDGS I",
      "cusip": "55405Y100",
      "shares": 1063,
      "value": 236060,
      "optionType": "STOCK",
      "typeInfo": {
        "label": "Stock",
        "badge": "bg-blue-100 text-blue-800 border-blue-200",
        "strategy": "equity"
      },
      "titleOfClass": "COM",
      "putCall": null
    },
    {
      "name": "NUSCALE PWR CORP",
      "cusip": "67079K100",
      "shares": 21246,
      "value": 230307,
      "optionType": "STOCK",
      "typeInfo": {
        "label": "Stock",
        "badge": "bg-blue-100 text-blue-800 border-blue-200",
        "strategy": "equity"
      },
      "titleOfClass": "CL A COM",
      "putCall": null
    },
    {
      "name": "SALESFORCE INC",
      "cusip": "79466L302",
      "shares": 1215,
      "value": 226859,
      "optionType": "STOCK",
      "typeInfo": {
        "label": "Stock",
        "badge": "bg-blue-100 text-blue-800 border-blue-200",
        "strategy": "equity"
      },
      "titleOfClass": "COM",
      "putCall": null
    },
    {
      "name": "AFFIRM HLDGS INC",
      "cusip": "00827B106",
      "shares": 4763,
      "value": 218241,
      "optionType": "STOCK",
      "typeInfo": {
        "label": "Stock",
        "badge": "bg-blue-100 text-blue-800 border-blue-200",
        "strategy": "equity"
      },
      "titleOfClass": "COM CL A",
      "putCall": null
    },
    {
      "name": "TALEN ENERGY CORP",
      "cusip": "87422Q109",
      "shares": 682,
      "value": 217715,
      "optionType": "STOCK",
      "typeInfo": {
        "label": "Stock",
        "badge": "bg-blue-100 text-blue-800 border-blue-200",
        "strategy": "equity"
      },
      "titleOfClass": "COM",
      "putCall": null
    },
    {
      "name": "SPDR SERIES TRUST",
      "cusip": "78468R663",
      "shares": 2286,
      "value": 209489,
      "optionType": "STOCK",
      "typeInfo": {
        "label": "Stock",
        "badge": "bg-blue-100 text-blue-800 border-blue-200",
        "strategy": "equity"
      },
      "titleOfClass": "STATE STREET SPD",
      "putCall": null
    },
    {
      "name": "QXO INC",
      "cusip": "82846H405",
      "shares": 10692,
      "value": 207639,
      "optionType": "STOCK",
      "typeInfo": {
        "label": "Stock",
        "badge": "bg-blue-100 text-blue-800 border-blue-200",
        "strategy": "equity"
      },
      "titleOfClass": "COM NEW",
      "putCall": null
    },
    {
      "name": "GRUPO FINANCIERO GALICIA S.A",
      "cusip": "399909100",
      "shares": 4388,
      "value": 204963,
      "optionType": "STOCK",
      "typeInfo": {
        "label": "Stock",
        "badge": "bg-blue-100 text-blue-800 border-blue-200",
        "strategy": "equity"
      },
      "titleOfClass": "SPONSORED ADR",
      "putCall": null
    },
    {
      "name": "EL POLLO LOCO HLDGS INC",
      "cusip": "268603107",
      "shares": 13132,
      "value": 182010,
      "optionType": "STOCK",
      "typeInfo": {
        "label": "Stock",
        "badge": "bg-blue-100 text-blue-800 border-blue-200",
        "strategy": "equity"
      },
      "titleOfClass": "COM",
      "putCall": null
    },
    {
      "name": "NAUTILUS BIOTECHNOLOGY INC",
      "cusip": "63909J108",
      "shares": 40345,
      "value": 156539,
      "optionType": "STOCK",
      "typeInfo": {
        "label": "Stock",
        "badge": "bg-blue-100 text-blue-800 border-blue-200",
        "strategy": "equity"
      },
      "titleOfClass": "COM",
      "putCall": null
    },
    {
      "name": "OPENDOOR TECHNOLOGIES INC",
      "cusip": "683712103",
      "shares": 17474,
      "value": 81778,
      "optionType": "STOCK",
      "typeInfo": {
        "label": "Stock",
        "badge": "bg-blue-100 text-blue-800 border-blue-200",
        "strategy": "equity"
      },
      "titleOfClass": "COM",
      "putCall": null
    }
  ],
  "totalValue": 14456164077,
  "positionsCount": 221,
  "portfolioSummary": {
    "byType": {
      "STOCK": 14456164077
    },
    "percentages": {
      "STOCK": "100.0%"
    }
  }
}