{
  "form": "13F-HR",
  "date": "2017-11-14",
  "period": "2017-11-14",
  "accession": "0001345471-17-000051",
  "quarterKey": "2017-Q4",
  "positions": [
    {
      "name": "Procter and Gamble Co.",
      "cusip": "742718109",
      "shares": 37908621,
      "value": 3448926
    },
    {
      "name": "Sysco Corp",
      "cusip": "871829107",
      "shares": 44492524,
      "value": 2400372
    },
    {
      "name": "Mondelez Intl Inc",
      "cusip": "609207105",
      "shares": 42504701,
      "value": 1728241
    },
    {
      "name": "General Electric Co.",
      "cusip": "369604103",
      "shares": 70851055,
      "value": 1713179
    },
    {
      "name": "Bank New York Mellon Corp",
      "cusip": "064058100",
      "shares": 22375489,
      "value": 1186348
    },
    {
      "name": "Pentair PLC",
      "cusip": "G7S00T104",
      "shares": 15200931,
      "value": 1033055
    },
    {
      "name": "DowDuPont Inc",
      "cusip": "26078J100",
      "shares": 12526545,
      "value": 867213
    },
    {
      "name": "Wendys Co.",
      "cusip": "95058W100",
      "shares": 39035921,
      "value": 606228
    }
  ],
  "totalValue": 12983562,
  "positionsCount": 8
}